pairplotr/__init__.py
pairplotr/pairplotr.py
pairplotr-1.3.dist-info/DESCRIPTION.rst
pairplotr-1.3.dist-info/METADATA
pairplotr-1.3.dist-info/RECORD
pairplotr-1.3.dist-info/WHEEL
pairplotr-1.3.dist-info/metadata.json
pairplotr-1.3.dist-info/top_level.txt
