Metadata-Version: 2.0
Name: pairplotr
Version: 1.3
Summary: Pairplotr is a Python library used to graph combinations of numerical and categorical data in a pair plot
Home-page: http://packages.python.org/pairplotr
Author: Christopher Shymansky
Author-email: CMShymansky@gmail.com
License: OSI Approved :: Apache Software License
Keywords: scikit-learn pandas data visualization pairplot
Platform: UNKNOWN
Classifier: Development Status :: 3 - Alpha
Classifier: Topic :: Utilities
Classifier: License :: OSI Approved :: Apache Software License
Requires-Dist: matplotlib
Requires-Dist: numpy
Requires-Dist: pandas
Requires-Dist: seaborn
